cram2wordnet/__init__.py
cram2wordnet/cram2wordnet.py
cram2wordnet-1.0.1.dist-info/LICENSE
cram2wordnet-1.0.1.dist-info/METADATA
cram2wordnet-1.0.1.dist-info/WHEEL
cram2wordnet-1.0.1.dist-info/top_level.txt
cram2wordnet-1.0.1.dist-info/RECORD
